[
  {
    "title": "Israel and Hezbollah agree ceasefire, US says, as more Lebanon strikes reported",
    "snippet": "The agreement followed concerns that continued clashes would undermine the deal to end the war between the US and Iran.",
    "category": "WORLD",
    "source": "Global Pulse Intelligence",
    "time": "6/19/2026, 7:27:12 PM",
    "imageUrl": "https://ichef.bbci.co.uk/ace/standard/240/cpsprodpb/1d8c/live/3048d450-6c0d-11f1-866d-31e44f099e94.jpg",
    "link": "#"
  },
  {
    "title": "Italy's Meloni says Trump 'made up' story that she 'begged' him for photo at G7",
    "snippet": "The highly public exchange is an indication that their earlier close ties have frayed  since Trump's decision to go to war with Iran.",
    "category": "WORLD",
    "source": "Global Pulse Intelligence",
    "time": "6/19/2026, 1:42:47 PM",
    "imageUrl": "https://ichef.bbci.co.uk/ace/standard/240/cpsprodpb/467b/live/b8c74c90-6bf3-11f1-b1db-af71d47507d6.jpg",
    "link": "#"
  },
  {
    "title": "US to end funding of South Africa's HIV programmes over claims of Afrikaner persecution",
    "snippet": "The US says South Africa is not doing enough to protect the white-minority Afrikaner community.",
    "category": "WORLD",
    "source": "Global Pulse Intelligence",
    "time": "6/19/2026, 5:02:02 PM",
    "imageUrl": "https://ichef.bbci.co.uk/ace/standard/240/cpsprodpb/6893/live/8c956090-6bf7-11f1-8bf6-931d18012412.jpg",
    "link": "#"
  },
  {
    "title": "Do it at home too, women tell Japanese fans who cleaned World Cup stadium",
    "snippet": "Some see a double standard: Japanese men who clean in public while their wives do all the housework.",
    "category": "WORLD",
    "source": "Global Pulse Intelligence",
    "time": "6/19/2026, 4:30:47 AM",
    "imageUrl": "https://ichef.bbci.co.uk/ace/standard/240/cpsprodpb/ce26/live/6d636b80-6b94-11f1-a202-c5e2a605690a.jpg",
    "link": "#"
  },
  {
    "title": "Six-year-old Ebola patient taken from DR Congo hospital found and 'doing well'",
    "snippet": "Health facilities have come under attack during the current outbreak as a result of misinformation and fear.",
    "category": "WORLD",
    "source": "Global Pulse Intelligence",
    "time": "6/19/2026, 2:45:57 PM",
    "imageUrl": "https://ichef.bbci.co.uk/ace/standard/240/cpsprodpb/defa/live/2098db00-6be4-11f1-b1db-af71d47507d6.jpg",
    "link": "#"
  },
  {
    "title": "Morocco captain Achraf Hakimi to stand trial for rape",
    "snippet": "French prosecutors confirm Morocco captain Achraf Hakimi will stand trial for rape, in accusations dating back to 2023.",
    "category": "WORLD",
    "source": "Global Pulse Intelligence",
    "time": "6/19/2026, 10:28:22 AM",
    "imageUrl": "https://ichef.bbci.co.uk/ace/standard/240/cpsprodpb/aba2/live/baf34430-6bba-11f1-8e5f-879143928516.jpg",
    "link": "#"
  },
  {
    "title": "Pétanque player, 68, dies after being 'hit in head with metal boule'",
    "snippet": "The man was allegedly struck by his 81-year-old opponent, who has since been arrested, the public prosecutor says.",
    "category": "WORLD",
    "source": "Global Pulse Intelligence",
    "time": "6/19/2026, 5:30:24 PM",
    "imageUrl": "https://ichef.bbci.co.uk/ace/standard/240/cpsprodpb/1132/live/b20aaa10-6bfc-11f1-8bf6-931d18012412.jpg",
    "link": "#"
  },
  {
    "title": "Boy, 12, wins hearts after trying to check sick chicken into Ethiopian hospital",
    "snippet": "Markos's beloved hen was not responding to any treatments - so he did the only thing he could think of.",
    "category": "WORLD",
    "source": "Global Pulse Intelligence",
    "time": "6/19/2026, 10:25:30 AM",
    "imageUrl": "https://ichef.bbci.co.uk/ace/standard/240/cpsprodpb/02fc/live/c5f90dd0-6bcc-11f1-8e1d-bbbb1017d210.jpg",
    "link": "#"
  },
  {
    "title": "Zimbabwe MPs pass bill to extend president's time in power",
    "snippet": "The proposal would extend Emmerson Mnangagwa's term by two years and scrap direct presidential elections.",
    "category": "WORLD",
    "source": "Global Pulse Intelligence",
    "time": "6/19/2026, 8:03:32 AM",
    "imageUrl": "https://ichef.bbci.co.uk/ace/standard/240/cpsprodpb/1153/live/7749ed00-6ba7-11f1-ad4f-418bfa76e5cc.jpg",
    "link": "#"
  },
  {
    "title": "UK actress charged with importing meth worth almost A$300m into Australia",
    "snippet": "Emaa Hussen, 34, faces life in prison for allegedly trying to smuggle 320kg of meth hidden in bags of charcoal.",
    "category": "WORLD",
    "source": "Global Pulse Intelligence",
    "time": "6/19/2026, 1:04:14 AM",
    "imageUrl": "https://ichef.bbci.co.uk/ace/standard/240/cpsprodpb/d405/live/a5d92360-6b76-11f1-8e1d-bbbb1017d210.jpg",
    "link": "#"
  },
  {
    "title": "UK's top data and AI regulator quits after 'inappropriate' humour",
    "snippet": "Edwards has been the boss of the data watchdog since January 2022, and said he had made inappropriate attempts at humour.",
    "category": "TECH",
    "source": "Global Pulse Intelligence",
    "time": "6/19/2026, 12:45:06 PM",
    "imageUrl": "https://ichef.bbci.co.uk/ace/standard/240/cpsprodpb/ce43/live/976528e0-6bc3-11f1-8e1d-bbbb1017d210.jpg",
    "link": "#"
  },
  {
    "title": "GTA 6 - all you need to know about Rockstar's blockbuster game",
    "snippet": "Rockstar's sixth game in the franchise is set to be the biggest game release of the year.",
    "category": "TECH",
    "source": "Global Pulse Intelligence",
    "time": "6/19/2026, 11:21:09 AM",
    "imageUrl": "https://ichef.bbci.co.uk/ace/standard/240/cpsprodpb/6ab0/live/49c33180-6bce-11f1-a94c-73f00a91c697.jpg",
    "link": "#"
  },
  {
    "title": "The artificial ice pyramids saving India's mountain villages",
    "snippet": "Himalayan villages are creating artificial glaciers to guarantee water for their crops in the spring.",
    "category": "TECH",
    "source": "Global Pulse Intelligence",
    "time": "6/18/2026, 11:11:07 PM",
    "imageUrl": "https://ichef.bbci.co.uk/ace/standard/240/cpsprodpb/ac70/live/f0de5b80-6015-11f1-89a3-d1f559421220.jpg",
    "link": "#"
  },
  {
    "title": "GTA 6 pre-order date and cover art revealed by Rockstar",
    "snippet": "The developer has said pre-sales of the hugely anticipated game will begin on 25 June.",
    "category": "TECH",
    "source": "Global Pulse Intelligence",
    "time": "6/18/2026, 2:06:48 PM",
    "imageUrl": "https://ichef.bbci.co.uk/ace/standard/240/cpsprodpb/34b6/live/03c3e400-6b19-11f1-be36-65d2d6d55e70.jpg",
    "link": "#"
  },
  {
    "title": "AI will create more jobs for humans, not replace them, Amazon founder Bezos says",
    "snippet": "The Amazon founder, who now has robotics and space travel companies, thinks AI will create a labour shortage.",
    "category": "TECH",
    "source": "Global Pulse Intelligence",
    "time": "6/17/2026, 4:37:41 PM",
    "imageUrl": "https://ichef.bbci.co.uk/ace/standard/240/cpsprodpb/1b53/live/14d94320-6a65-11f1-8e1d-bbbb1017d210.jpg",
    "link": "#"
  }
]